idmapshift
