Metadata-Version: 1.1
Name: IDMapShift
Version: 0.0.2
Summary: Tool to properly chown filesystems for use with user namespaces.
Home-page: https://github.com/ramielrowe/idmapshift
Author: Andrew Melton
Author-email: andrew.melton@rackspace.com
License: Apache
Keywords: user namespaces idmap containers
Platform: UNKNOWN
Classifier: Development Status :: 3 - Alpha
Classifier: Topic :: Utilities
Classifier: License :: OSI Approved :: Apache Software License
Classifier: Operating System :: POSIX :: Linux
